genomic_embeddings/Embeddings.py
genomic_embeddings/Gff.py
genomic_embeddings/__init__.py
genomic_embeddings/corpus.py
genomic_embeddings/data.py
genomic_embeddings/gene2vec.py
genomic_embeddings/models.py
genomic_embeddings/plot.py
genomic_embeddings-0.0.4.dist-info/METADATA
genomic_embeddings-0.0.4.dist-info/WHEEL
genomic_embeddings-0.0.4.dist-info/licenses/LICENSE
genomic_embeddings-0.0.4.dist-info/RECORD
