Metadata-Version: 2.1
Name: genomic_embeddings
Version: 0.0.4
Summary: Package supporting the paper Deciphering microbial gene function using natural language processing
Project-URL: GitHub, https://github.com/burstein-lab/genomic-nlp
Author-email: Danielle Miller Sayag <danimillers10@gmail.com>
Classifier: License :: OSI Approved :: GNU General Public License v3 (GPLv3)
Classifier: Operating System :: OS Independent
Classifier: Programming Language :: Python :: 3
Requires-Python: >=3.7
